LICENSE
joblibgcs/__init__.py
joblibgcs/gcs_backend.py
joblibgcs-0.2.0.dist-info/LICENSE
joblibgcs-0.2.0.dist-info/WHEEL
joblibgcs-0.2.0.dist-info/METADATA
joblibgcs-0.2.0.dist-info/RECORD
