Metadata-Version: 2.1
Name: joblibgcs
Version: 0.2.0
Summary: a google cloud storage memory backend for joblib
Home-page: https://gitlab.com/gautas/joblibgcs
License: MIT
Keywords: joblib storage backend,google cloud storage
Author: Gautam Sisodia
Author-email: gautam.sisodia@gmail.com
Requires-Python: >=3.10,<4.0
Classifier: License :: OSI Approved :: MIT License
Classifier: Programming Language :: Python :: 3
Classifier: Programming Language :: Python :: 3.10
Provides-Extra: book
Requires-Dist: gcsfs (>=2022.7.1,<2023.0.0)
Requires-Dist: ipykernel (>=6.15.1,<7.0.0); extra == "book"
Requires-Dist: joblib (>=1.1.0,<2.0.0)
Project-URL: Repository, https://gitlab.com/gautas/joblibgcs
